cli.py
rpdk/__init__.py
rpdk/guard_rail/__init__.py
rpdk/guard_rail/core/__init__.py
rpdk/guard_rail/core/data_types.py
rpdk/guard_rail/core/runner.py
rpdk/guard_rail/core/stateful.py
rpdk/guard_rail/rule_library/__init__.py
rpdk/guard_rail/rule_library/combiners/__init__.py
rpdk/guard_rail/rule_library/combiners/schema-linter-combiner-rules.guard
rpdk/guard_rail/rule_library/core/__init__.py
rpdk/guard_rail/rule_library/core/schema-linter-core-arn-rules.guard
rpdk/guard_rail/rule_library/core/schema-linter-core-permission-rules.guard
rpdk/guard_rail/rule_library/core/schema-linter-core-rules.guard
rpdk/guard_rail/rule_library/mutable/__init__.py
rpdk/guard_rail/rule_library/mutable/schema-linter-mutable-permission-rules.guard
rpdk/guard_rail/rule_library/mutable/schema-linter-mutable-rules.guard
rpdk/guard_rail/rule_library/stateful/__init__.py
rpdk/guard_rail/rule_library/stateful/schema-stateful-cfn-enforced-checks.guard
rpdk/guard_rail/rule_library/stateful/schema-stateful-non-cfn-enforced-checks.guard
rpdk/guard_rail/rule_library/tags/__init__.py
rpdk/guard_rail/rule_library/tags/schema-linter-core-tagging-rules.guard
rpdk/guard_rail/utils/__init__.py
rpdk/guard_rail/utils/arg_handler.py
rpdk/guard_rail/utils/common.py
rpdk/guard_rail/utils/logger.py
rpdk/guard_rail/utils/schema_utils.py
resource_schema_guard_rail-0.0.20.dist-info/LICENSE
resource_schema_guard_rail-0.0.20.dist-info/METADATA
resource_schema_guard_rail-0.0.20.dist-info/WHEEL
resource_schema_guard_rail-0.0.20.dist-info/entry_points.txt
resource_schema_guard_rail-0.0.20.dist-info/top_level.txt
resource_schema_guard_rail-0.0.20.dist-info/RECORD
