Metadata-Version: 2.1
Name: resource-schema-guard-rail
Version: 0.0.20
Summary: Schema Guard Rail
Home-page: UNKNOWN
Author: Amazon Web Services
Author-email: aws-cloudformation-developers@amazon.com
License: Apache License 2.0
Platform: UNKNOWN
Classifier: Development Status :: 4 - Beta
Classifier: Programming Language :: Python :: 3.8
Classifier: Programming Language :: Python :: 3.9
Classifier: Programming Language :: Python :: 3.10
Classifier: Intended Audience :: Developers
Classifier: License :: OSI Approved :: Apache Software License
Classifier: Natural Language :: English
Requires-Python: >=3.7
Requires-Dist: cfn-guard-rs==0.1.2
Requires-Dist: coverage>=4.5.4
Requires-Dist: deepdiff==5.8.0
Requires-Dist: jsonschema<4.0,>=3.0.1
Requires-Dist: pip>=23.3
Requires-Dist: pre-commit>=2.21.0
Requires-Dist: pylint>=2.15.10
Requires-Dist: pytest-cov>=4.0.0
Requires-Dist: pytest-random-order>=1.1.0
Requires-Dist: pytest>=7.2.0
Requires-Dist: rich==13.7.1
Requires-Dist: StrEnum==0.4.10
Requires-Dist: wheel==0.38.1
